pyansys/__init__.py
pyansys-2025.2.5.dist-info/licenses/LICENSE
pyansys-2025.2.5.dist-info/WHEEL
pyansys-2025.2.5.dist-info/METADATA
pyansys-2025.2.5.dist-info/RECORD
