Metadata-Version: 2.4
Name: pyansys
Version: 2025.2.5
Summary: Pythonic interfaces to Ansys products
Author-email: "ANSYS, Inc." <pyansys.support@ansys.com>
Maintainer-email: PyAnsys developers <pyansys.maintainers@ansys.com>
Requires-Python: >=3.10,<4
Classifier: Development Status :: 4 - Beta
Classifier: Intended Audience :: Science/Research
Classifier: Topic :: Scientific/Engineering :: Information Analysis
Classifier: License :: OSI Approved :: MIT License
Classifier: Operating System :: OS Independent
Classifier: Programming Language :: Python :: 3.10
Classifier: Programming Language :: Python :: 3.11
Classifier: Programming Language :: Python :: 3.12
Classifier: Programming Language :: Python :: 3.13
License-File: LICENSE
Requires-Dist: ansys-acp-core==0.3.0
Requires-Dist: ansys-additive-core==0.20.0
Requires-Dist: ansys-conceptev-core==0.9.4
Requires-Dist: ansys-dpf-composites==0.7.0
Requires-Dist: ansys-dpf-core==0.15.0
Requires-Dist: ansys-dpf-post==0.11.0
Requires-Dist: ansys-dyna-core==0.9.0
Requires-Dist: ansys-dynamicreporting-core==0.10.1
Requires-Dist: ansys-edb-core==0.2.4
Requires-Dist: ansys-fluent-core==0.34.3
Requires-Dist: ansys-geometry-core==0.14.1
Requires-Dist: ansys-hps-client==0.10.1
Requires-Dist: ansys-hps-data-transfer-client==0.2.1
Requires-Dist: ansys-mapdl-core==0.70.2
Requires-Dist: ansys-math-core==0.2.4
Requires-Dist: ansys-mechanical-core==0.12.0
Requires-Dist: ansys-meshing-prime==0.9.4
Requires-Dist: ansys-modelcenter-workflow==0.1.3
Requires-Dist: ansys-motorcad-core==0.7.4
Requires-Dist: ansys-optislang-core==1.0.0
Requires-Dist: ansys-platform-instancemanagement==1.1.2
Requires-Dist: ansys-pyensight-core==0.10.0.post1
Requires-Dist: ansys-rocky-core==0.3.2
Requires-Dist: ansys-seascape==0.2.0
Requires-Dist: ansys-sherlock-core==0.9.0
Requires-Dist: ansys-simai-core==0.3.3
Requires-Dist: ansys-sound-core==0.2.1
Requires-Dist: ansys-speos-core==0.7.0
Requires-Dist: ansys-stk==0.2.1
Requires-Dist: ansys-systemcoupling-core==0.11.2
Requires-Dist: ansys-turbogrid-core==0.4.6
Requires-Dist: ansys-workbench-core==0.10.0
Requires-Dist: pyaedt==0.23.0
Requires-Dist: pyedb==0.54.0
Requires-Dist: pygranta==2025.2.1
Requires-Dist: pytwin==0.9.2
Requires-Dist: ansys-mapdl-reader==0.55.1 ; extra == "all"
Requires-Dist: ansys-fluent-visualization==0.21.1 ; extra == "all"
Requires-Dist: ansys-materials-manager==0.3.0 ; extra == "all"
Requires-Dist: ansys-tools-filetransfer==0.2.0 ; extra == "all"
Requires-Dist: ansys-tools-local-product-launcher==0.2.0 ; extra == "all"
Requires-Dist: ansys-tools-path==0.7.3 ; extra == "all"
Requires-Dist: ansys-tools-visualization-interface==0.11.0 ; extra == "all"
Requires-Dist: ansys-units==0.7.0 ; extra == "all"
Requires-Dist: pyansys-tools-report==0.8.2 ; extra == "all"
Requires-Dist: pyansys-tools-versioning==0.6.0 ; extra == "all"
Requires-Dist: pyansys-tools-variableinterop==0.1.2 ; extra == "all"
Requires-Dist: Sphinx==8.2.3 ; extra == "doc"
Requires-Dist: ansys-sphinx-theme==1.5.3 ; extra == "doc"
Requires-Dist: Jinja2 ==3.1.6 ; extra == "doc"
Requires-Dist: Pillow==11.3.0 ; extra == "doc"
Requires-Dist: PyGithub==2.7.0 ; extra == "doc"
Requires-Dist: sphinx-copybutton==0.5.2 ; extra == "doc"
Requires-Dist: sphinx-design==0.6.1 ; extra == "doc"
Requires-Dist: sphinxcontrib-mermaid==1.0.0 ; extra == "doc"
Requires-Dist: sphinx-jinja==2.0.2 ; extra == "doc"
Requires-Dist: ansys-fluent-visualization==0.21.1 ; extra == "fluent-all"
Requires-Dist: ansys-mapdl-reader==0.55.1 ; extra == "mapdl-all"
Requires-Dist: ansys-materials-manager==0.3.0 ; extra == "tools"
Requires-Dist: ansys-tools-filetransfer==0.2.0 ; extra == "tools"
Requires-Dist: ansys-tools-local-product-launcher==0.2.0 ; extra == "tools"
Requires-Dist: ansys-tools-path==0.7.3 ; extra == "tools"
Requires-Dist: ansys-tools-visualization-interface==0.11.0 ; extra == "tools"
Requires-Dist: ansys-units==0.7.0 ; extra == "tools"
Requires-Dist: pyansys-tools-report==0.8.2 ; extra == "tools"
Requires-Dist: pyansys-tools-versioning==0.6.0 ; extra == "tools"
Requires-Dist: pyansys-tools-variableinterop==0.1.2 ; extra == "tools"
Project-URL: Documentation, https://docs.pyansys.com
Project-URL: Source, https://github.com/ansys/pyansys
Provides-Extra: all
Provides-Extra: doc
Provides-Extra: fluent-all
Provides-Extra: mapdl-all
Provides-Extra: tools
